RD_STT/__init__.py
RD_STT-2.1.dist-info/METADATA
RD_STT-2.1.dist-info/WHEEL
RD_STT-2.1.dist-info/top_level.txt
RD_STT-2.1.dist-info/RECORD
