Metadata-Version: 2.1
Name: RD_STT
Version: 2.1
Summary: This is a speech-to-text package created by Ritik Dwivedi
Author: Ritik Dwivedi
Author-email: example@gmail.com
Requires-Dist: selenium
Requires-Dist: webdriver-manager
